{
  "data": [
    {
      "url": "/work/binge",
      "title": "Binge -- Online chat",
      "brief": "Binge(品各)是一款以AR为核心的交友APP，包括美食分享，好友配对，地图寻宝，暂已下线",
      "cover": "binge.jpg",
      "type": 1,
      "tags": [
        "PROJECT",
        "ANDROID",
        "PUBLISHED"
      ]
    },
    {
      "url": "/work/fro",
      "title": "Fro -- Express Delivery",
      "brief": "Fro(飞赴)是一款以快递O2O模式为核心打造的多样化周边服务的APP，已上线各大应用商店",
      "cover": "fro.jpg",
      "type": 1,
      "tags": [
        "PROJECT",
        "ANDROID",
        "PUBLISHED"
      ],
      "links": [
        {
          "name": "Website",
          "url": "http://theappfro.com/"
        },
        {
          "name": "Download",
          "url": "http://theappfro.com/web/newDownload"
        }
      ]
    },
    {
      "url": "/work/video-editor",
      "title": "Video Editor",
      "brief": "基于FFmpeg的视频编辑软件，继承了视频截取、混音以及缩放裁剪等功能，可导出多种格式",
      "cover": "video-editor.jpg",
      "type": 1,
      "tags": [
        "PROJECT",
        "ANDROID"
      ]
    },
    {
      "url": "/work/balloon",
      "title": "Balloon",
      "brief": "快递APP，UI和UX概念设计",
      "cover": "balloon.jpg",
      "type": 1,
      "tags": [
        "DESIGN",
        "XD",
        "UI"
      ]
    },
    {
      "url": "/work/dashboard",
      "title": "Dashboard",
      "brief": "后台事务管理，数据统计",
      "cover": "dashboard.jpg",
      "type": 1,
      "tags": [
        "DESIGN",
        "WEB"
      ]
    }
  ]
}